{"title":"What’s !important #2: Conditional View Transitions, CSS/SVG Text Effects, the Best of CSS Bluesky, and More","content":"<body>\n    <p>2026년을 앞두고 지난 2주간의 CSS 관련 주요 소식들을 요약합니다.</p>\n    <ul>\n        <li>\n            <p><strong>조건부 뷰 전환:</strong></p>\n            <p>Chris Coyier는 URL이나 JavaScript 로직에 따라 다른 뷰 전환을 트리거하는 방법을 소개했습니다. Bramus는 CSS 자체적으로도 네비게이션 매칭 기능이 곧 지원될 것이라고 언급하여, JavaScript 의존도를 낮출 가능성이 있습니다.</p>\n        </li>\n        <li>\n            <p><strong>디자인 시스템 컴포넌트의 접근성 주석 달기:</strong></p>\n            <p>Geri Reid는 디자인 시스템 컴포넌트에 접근성을 위한 주석을 다는 방법을 HTML 예시와 함께 상세히 설명했습니다. 특히 요소, ARIA, 마크업, 키보드 네비게이션, 줌, 사용자 설정 등을 접근성 토큰으로 정의하는 부분이 인상적입니다. (출처: zeroheight)</p>\n        </li>\n        <li>\n            <p><strong>Firefox의 AI 브라우저 전환과 반발:</strong></p>\n            <p>Firefox의 새로운 CEO가 Firefox를 \"현대적인 AI 브라우저\"로 발전시키겠다고 발표했지만, 사용자들의 반응은 부정적입니다. 이에 Firefox는 AI 킬 스위치 기능을 발표했습니다. (관련 내용: The Verge 인터뷰)</p>\n            <p>AI 없는 Firefox 포크인 Waterfox도 언급되었습니다.</p>\n        </li>\n        <li>\n            <p><strong>CSS와 SVG를 이용한 '툰 텍스트' 만들기:</strong></p>\n            <p>Andy Clarke는 CSS와 SVG를 활용하여 고전 만화 스타일의 텍스트 효과를 만드는 방법을 시연했습니다. 특히 `paint-order` CSS 속성이 새롭게 소개되었습니다. (출처: Smashing Magazine)</p>\n        </li>\n        <li>\n            <p><strong>2025년에 배워야 할 CSS 기능:</strong></p>\n            <p>Adam Argyle은 2025년에 학습해야 할 CSS 기능에 대해 논했으며, `@property`와 같은 기능에 대한 언급이 있었습니다. (출처: CSS-Tricks)</p>\n        </li>\n        <li>\n            <p><strong>Bluesky의 훌륭한 CSS 게시물:</strong></p>\n            <p>소셜 미디어 환경에 대한 언급과 함께 Bluesky에서 공유된 유용한 CSS 관련 게시물들이 소개되었습니다.</p>\n            <ul>\n                <li>\n                    <p><strong>Temani Afif:</strong> 앵커 포지셔닝, `attr()`, 컨테이너 쿼리, `shape()` 등 현대적인 CSS 기능을 결합한 흥미로운 데모를 선보였습니다. (출처: css-tip.com/connected-ci…)</p>\n                    <p><strong>관련 트윗:</strong> CSS by T. Afif (@css-only.dev) 2025-12-16T11:21:17.632Z</p>\n                </li>\n                <li>\n                    <p><strong>Stephen Margheim:</strong> 시맨틱 클래스에 네임스페이스를 사용하는 이유를 설명했습니다 (예: `.btn` 대신 `.ui-button`).</p>\n                    <p><strong>관련 트윗:</strong> Stephen Margheim (@fractaledmind.bsky.social) 2025-12-25T11:02:03.013434Z</p>\n                </li>\n                <li>\n                    <p><strong>Ana Tudor:</strong> 변위 맵(displacement map)을 이용한 놀라운 텍스트 효과를 소개했습니다. (Chrome에서 잘 작동하며, 다양한 효과 데모 제공)</p>\n                    <p><strong>관련 트윗:</strong> Ana Tudor (@anatudor.bsky.social) 2025-12-26T11:41:39.033Z</p>\n                </li>\n                <li>\n                    <p><strong>George Black:</strong> Chrome 또는 Safari에서만 사용 가능한 최신 CSS 기능을 사용하여 웹사이트를 개발하는 상황과 그에 따른 \"최종 일관성\"에 대해 언급했습니다.</p>\n                    <p><strong>관련 트윗:</strong> George Black (@george.black) 2025-12-28T21:14:06.209Z</p>\n                    <p><strong>추가 정보:</strong> Chrome, Firefox, Safari 간의 기능 일관성을 위한 Interop Project에 대한 설명과 Interop 2026에 대한 언급이 있었습니다.</p>\n                </li>\n                <li>\n                    <p><strong>Sunkanmi Fafowora:</strong> CSS의 경계를 넓히는 개발자들에게 감사를 표했습니다.</p>\n                    <p><strong>관련 트윗:</strong> Sunkanmi Fafowora (@sunkanmifafowora.bsky.social) 2025-12-17T12:26:42.271Z</p>\n                </li>\n            </ul>\n        </li>\n    </ul>\n    <p>CSS-Tricks 팀은 새해를 맞이하며 버그 없고 모든 브라우저에서 잘 작동하는 웹사이트를 기원합니다. 2026년에 다시 만나요!</p>\n    <p>원본 기사는 CSS-Tricks에서 발행되었으며, DigitalOcean의 일부입니다. (뉴스레터 구독 권장)</p>\n</body>","createdAt":"2025-12-31T16:18:23.000+00:00","link":"https://css-tricks.com/whats-important-2/","language":"ko"}