{"title":"The “Most Hated” CSS Feature: asin(), acos(), atan() and atan2()","content":"<body>\n<p>이 글은 CSS의 역삼각함수인 asin(), acos(), atan(), atan2()에 대한 내용을 다룹니다. 이전 글에서 sin(), cos(), tan() 함수를 다룬 후, 이번에는 이 함수들의 역함수를 통해 각도를 구하는 방법을 살펴봅니다.</p>\n\n<h2>역삼각함수란?</h2>\n<ul>\n<li>cos(θ), sin(θ), tan(θ)는 각도를 입력받아 해당 각도의 코사인, 사인, 탄젠트 값을 반환합니다.</li>\n<li>역삼각함수는 반대로 특정 삼각함수 값을 입력받아 원래의 각도를 반환합니다.</li>\n<li>acos()는 cos()의 역함수, asin()은 sin()의 역함수, atan()과 atan2()는 tan()의 역함수입니다.</li>\n<li>이 함수들은 '아크' 함수라고도 불리며, 원에서 특정 값에 해당하는 호(arc)의 각도를 구하는 것과 같습니다.</li>\n</ul>\n\n<h2>acos()와 asin()</h2>\n<ul>\n<li>acos()와 asin()은 -1에서 1 사이의 값만 입력받을 수 있습니다.</li>\n<li>acos()는 0°에서 180° 사이의 각도를 반환하고, asin()은 -90°에서 90° 사이의 각도를 반환합니다.</li>\n<li>이러한 제한 때문에 acos()와 asin()은 적용할 수 있는 상황이 제한적입니다.</li>\n</ul>\n\n<h2>atan()과 atan2()</h2>\n<ul>\n<li>atan()은 모든 실수 값을 입력받아 -90°에서 90° 사이의 각도를 반환합니다.</li>\n<li>atan()은 acos()와 asin()보다 훨씬 활용도가 높아 다양한 상황에서 각도를 구하는 데 사용됩니다.</li>\n<li>atan2()는 atan()과 유사하지만, 두 개의 인자를 받아 더 넓은 범위의 각도를 정확하게 계산할 수 있습니다.</li>\n</ul>\n\n<h2>atan() 활용 예시: 그라데이션 각도 계산</h2>\n<ul>\n<li><strong>선형 그라데이션:</strong> <code>to top right</code> 와 같은 키워드로 모서리에서 모서리로 가는 그라데이션 각도를 쉽게 설정할 수 있습니다.</li>\n<li><strong>원형 그라데이션:</strong> CSS의 <code>conic-gradient()</code> 함수에서 요소의 크기에 맞춰 동적으로 각도를 설정하기 위해 <code>atan()</code>을 사용할 수 있습니다. 요소의 너비(adjacent)와 높이(opposite)를 이용하여 각도를 계산합니다.</li>\n<li><strong>복잡한 원형 그라데이션:</strong> Ana Tudor의 'Variable Aspect Ratio Card With Conic Gradients' 예시처럼, <code>atan()</code>을 사용하여 복잡하고 역동적인 원형 그라데이션을 만들 수 있습니다.</li>\n</ul>\n\n<h2>atan2() 활용 예시: 마우스 추적</h2>\n<ul>\n<li><code>atan2(y, x)</code> 함수는 x, y 좌표를 각각 인자로 받아 어떤 사분면에 있든 정확한 각도를 계산합니다.</li>\n<li><strong>마우스 포인터 추적:</strong> JavaScript를 사용하여 마우스의 x, y 좌표를 CSS 사용자 정의 속성(--m-x, --m-y)으로 전달하고, <code>atan2()</code>를 이용하여 요소의 눈이나 다른 부분을 마우스 포인터를 향하도록 회전시킬 수 있습니다.</li>\n<li><strong>좌표계 원점 조정:</strong> 요소의 위치나 크기를 고려하여 좌표계의 원점을 조정하여 더욱 정확한 추적이 가능합니다.</li>\n</ul>\n\n<h2>추가: 뷰포트 크기를 숫자로 얻기</h2>\n<ul>\n<li><code>atan2()</code>와 <code>tan()</code>을 활용하여 <code>100vw</code>와 같은 단위를 정수형 숫자로 변환하는 트릭이 소개됩니다. (Jane Ori의 글 참조)</li>\n</ul>\n\n<h2>삼각함수의 역수</h2>\n<ul>\n<li>sec(x) = 1 / cos(x)</li>\n<li>csc(x) = 1 / sin(x)</li>\n<li>cot(x) = 1 / tan(x)</li>\n</ul>\n\n<p>이 시리즈는 CSS에서 삼각함수와 역삼각함수를 활용하여 다양한 시각적 효과를 구현하는 방법을 보여주며 마무리됩니다.</p>\n</body>\n```","createdAt":"2025-11-17T14:47:54.000+00:00","link":"https://css-tricks.com/the-most-hated-css-feature-asin-acos-atan-and-atan2/","language":"ko"}